zhengyang_env_5/__init__.py
zhengyang_env_5/envs/__init__.py
zhengyang_env_5/envs/kuka.py
zhengyang_env_5/envs/zhengyang_env_5.py
zhengyang_env_5-0.0.2.dist-info/METADATA
zhengyang_env_5-0.0.2.dist-info/WHEEL
zhengyang_env_5-0.0.2.dist-info/top_level.txt
zhengyang_env_5-0.0.2.dist-info/RECORD
